powermake/__init__.py
powermake/__main__.py
powermake/__version__.py
powermake/architecture.py
powermake/args_parser.py
powermake/cache.py
powermake/config.py
powermake/display.py
powermake/exceptions.py
powermake/interactive_config.py
powermake/operation.py
powermake/py.typed
powermake/search_visual_studio.py
powermake/tools.py
powermake/utils.py
powermake/archivers/README.md
powermake/archivers/__init__.py
powermake/archivers/common.py
powermake/archivers/gnu.py
powermake/archivers/msvc.py
powermake/compilers/README.md
powermake/compilers/__init__.py
powermake/compilers/asm.py
powermake/compilers/common.py
powermake/compilers/gnu.py
powermake/compilers/msvc.py
powermake/compilers/rc.py
powermake/generation/__init__.py
powermake/generation/compile_commands.py
powermake/generation/gnu_makefile.py
powermake/generation/powermake.py
powermake/generation/vscode.py
powermake/linkers/README.md
powermake/linkers/__init__.py
powermake/linkers/common.py
powermake/linkers/gnu.py
powermake/linkers/msvc.py
powermake/shared_linkers/README.md
powermake/shared_linkers/__init__.py
powermake/shared_linkers/common.py
powermake/shared_linkers/gnu.py
powermake/shared_linkers/msvc.py
powermake-2.10.1.dist-info/METADATA
powermake-2.10.1.dist-info/WHEEL
powermake-2.10.1.dist-info/entry_points.txt
powermake-2.10.1.dist-info/licenses/LICENSE.txt
powermake-2.10.1.dist-info/RECORD
