Metadata-Version: 2.4
Name: powermake
Version: 2.10.1
Summary: Yet another makefile tool. This one is meant to be super fast, super easy and crossplatform while leaving full power to the user at any time.
Project-URL: Homepage, https://github.com/mactul/powermake
Project-URL: Issues, https://github.com/mactul/powermake/issues
Author: Macéo Tuloup
License-File: LICENSE.txt
Classifier: License :: OSI Approved :: Apache Software License
Classifier: Operating System :: OS Independent
Classifier: Programming Language :: Python :: 3
Requires-Python: >=3.6
Requires-Dist: colorama
